setup.py
CCB/__init__.py
CCB.py.egg-info/PKG-INFO
CCB.py.egg-info/SOURCES.txt
CCB.py.egg-info/dependency_links.txt
CCB.py.egg-info/top_level.txt