Metadata-Version: 2.1
Name: CCB.py
Version: 115
Summary: [我是一隻小貓]
Home-page: UNKNOWN
Author: moon-start
Author-email: moon-start@gmail.com
License: LGPL
Platform: UNKNOWN
